{
  "slug": "joyful-noise",
  "title": "Joyful Noise",
  "status": "published",
  "scripture": "Psalm 100",
  "book": "Psalms",
  "cover": "joyful-noise.jpg",
  "audio": "joyful-noise.mp3",
  "spotify": "https://open.spotify.com/track/0QmofDfi8okM1Mruf0vuTS",
  "sections": [
    {
      "label": "Lyrics",
      "lines": [
        [
          null,
          "Make a joyful noise to the Lord, all the earth,"
        ],
        [
          null,
          "Serve Him with gladness, for all He’s worth."
        ],
        [
          null,
          "Come into His presence with songs of praise,"
        ],
        [
          null,
          "Our hearts uplifted, our voices raised."
        ],
        [
          null,
          "Know that the Lord is our mighty King,"
        ],
        [
          null,
          "He made us all; to Him we bring."
        ],
        [
          null,
          "We are His people, His pasture’s sheep,"
        ],
        [
          null,
          "Forever loved, His word we keep."
        ],
        [
          null,
          "Enter His gates with thanksgiving, true,"
        ],
        [
          null,
          "His courts with praise for all He’ll do."
        ],
        [
          null,
          "Give thanks to His name, bless it always,"
        ],
        [
          null,
          "For endless mercy fills our days."
        ],
        [
          null,
          "For the Lord is good, His love remains,"
        ],
        [
          null,
          "Through all the ages, His truth sustains."
        ],
        [
          null,
          "Know that the Lord is our mighty King,"
        ],
        [
          null,
          "He made us all; to Him we bring."
        ],
        [
          null,
          "We are His people, His pasture’s sheep,"
        ],
        [
          null,
          "Forever loved, His word we keep."
        ],
        [
          null,
          "Shout with joy to the Lord above,"
        ],
        [
          null,
          "Sing His truth and endless love."
        ]
      ]
    }
  ],
  "epigraph": "Make a joyful noise unto the LORD",
  "epigraphRef": "Psalm 100:1",
  "lyricEyebrow": "From the Psalms",
  "styleNote": "String Guitar And Clarinet · Darbuka Rhythms Grow Steady · All Voices Join Together"
}