{
  "slug": "out-of-the-belly-of-hell",
  "title": "Out Of The Belly Of Hell",
  "status": "published",
  "scripture": "Jonah 2",
  "book": "Jonah",
  "cover": "out-of-the-belly-of-hell.jpg",
  "audio": "out-of-the-belly-of-hell.mp3",
  "spotify": "",
  "sections": [
    {
      "label": "Verse 1",
      "lines": [
        [
          null,
          "I bought my passage with a borrowed name,"
        ],
        [
          null,
          "I turned my shoulder from the word."
        ],
        [
          null,
          "The wind came looking and it knew my shame,"
        ],
        [
          null,
          "and every prayer but mine was heard."
        ],
        [
          null,
          "They cast the lot and the lot fell true,"
        ],
        [
          null,
          "they raised me like a sheaf of grain."
        ],
        [
          null,
          "And I opened. And I took him in."
        ],
        [
          null,
          "And the deck went quiet in the rain."
        ]
      ]
    },
    {
      "label": "Chorus",
      "lines": [
        [
          null,
          "Out of the belly of hell I cried,"
        ],
        [
          null,
          "and Thou didst hear my voice."
        ],
        [
          null,
          "Under the roots of the world I cried,"
        ],
        [
          null,
          "and Thou didst hear my voice."
        ],
        [
          null,
          "(No lantern, no window, no bell, no light)"
        ],
        [
          null,
          "nothing of mine but my voice."
        ],
        [
          null,
          "And Thou didst hear my voice."
        ]
      ]
    },
    {
      "label": "Verse 2",
      "lines": [
        [
          null,
          "I put my billows and my waves on you,"
        ],
        [
          null,
          "I closed my floods on every side."
        ],
        [
          null,
          "I wrapped the weeds about your head"
        ],
        [
          null,
          "in the green and patient dark of the tide."
        ],
        [
          null,
          "I carried you to the mountains' roots,"
        ],
        [
          null,
          "I set the bars of the earth in place."
        ],
        [
          null,
          "Cast out of Thy sight. And yet. And yet."
        ],
        [
          null,
          "I will look again toward Thy holy temple."
        ]
      ]
    },
    {
      "label": "Chorus",
      "lines": [
        [
          null,
          "Out of the belly of hell I cried,"
        ],
        [
          null,
          "and Thou didst hear my voice."
        ],
        [
          null,
          "Under the roots of the world I cried,"
        ],
        [
          null,
          "and Thou didst hear my voice."
        ],
        [
          null,
          "And Thou didst hear my voice."
        ]
      ]
    },
    {
      "label": "Bridge",
      "lines": [
        [
          null,
          "When my soul fainted in me, I remembered."
        ],
        [
          null,
          "I felt it. A lamp lit under water."
        ],
        [
          null,
          "Not a creed. Not a name. I remembered."
        ],
        [
          null,
          "I was told to hold you. Not to keep you."
        ],
        [
          null,
          "They that run after lying vanities"
        ],
        [
          null,
          "forsake the mercy of their own two hands."
        ],
        [
          null,
          "I was never mine. I was only sent."
        ],
        [
          null,
          "So was the wind. So was the wave. So was I."
        ]
      ]
    },
    {
      "label": "Chorus",
      "lines": [
        [
          null,
          "Out of the belly of hell I cried,"
        ],
        [
          null,
          "and Thou hast heard my voice."
        ],
        [
          null,
          "Out of the grave of the world I cried,"
        ],
        [
          null,
          "and Thou hast heard my voice."
        ],
        [
          null,
          "What I vowed in the dark I will pay in the light."
        ],
        [
          null,
          "He has heard your voice."
        ],
        [
          null,
          "Thou hast heard my voice."
        ]
      ]
    },
    {
      "label": "Outro",
      "lines": [
        [
          null,
          "He spake to the fish, and I let go."
        ],
        [
          null,
          "The morning was a plain grey shore."
        ],
        [
          null,
          "The road runs east. I mean to walk it."
        ],
        [
          null,
          "Salvation is of the LORD."
        ]
      ]
    }
  ],
  "epigraph": "out of the belly of hell cried I",
  "epigraphRef": "Jonah 2:2",
  "lyricEyebrow": "From the Book of Jonah"
}